spacetransformer/torch/__init__.py
spacetransformer/torch/_version.py
spacetransformer/torch/affine_builder.py
spacetransformer/torch/gpu_utils.py
spacetransformer/torch/image_warpers.py
spacetransformer/torch/utils.py
spacetransformer/torch/validation.py
spacetransformer_torch-0.2.4.dist-info/METADATA
spacetransformer_torch-0.2.4.dist-info/WHEEL
spacetransformer_torch-0.2.4.dist-info/top_level.txt
spacetransformer_torch-0.2.4.dist-info/RECORD
