Metadata-Version: 2.4
Name: spacetransformer-torch
Version: 0.2.4
Summary: Torch accelerated resampling and grid building for Space Transformer.
Author-email: Fangzhou Liao <liaofz@fastdiag.ai>
License: MIT
Keywords: medical-imaging,geometry,transform,torch,gpu
Classifier: Development Status :: 3 - Alpha
Classifier: Intended Audience :: Developers
Classifier: License :: OSI Approved :: MIT License
Classifier: Programming Language :: Python :: 3
Classifier: Programming Language :: Python :: 3.8
Classifier: Programming Language :: Python :: 3.9
Classifier: Programming Language :: Python :: 3.10
Classifier: Programming Language :: Python :: 3.11
Classifier: Programming Language :: Python :: 3.12
Requires-Python: >=3.8
Requires-Dist: torch>=1.12
Requires-Dist: spacetransformer-core>=0.2.4
Provides-Extra: test
Requires-Dist: pytest; extra == "test"
Provides-Extra: dev
Requires-Dist: pytest; extra == "dev"
